MANIFEST.in
README.md
requirements-dev.txt
requirements.txt
setup.cfg
setup.py
brigade/__init__.py
brigade.egg-info/PKG-INFO
brigade.egg-info/SOURCES.txt
brigade.egg-info/dependency_links.txt
brigade.egg-info/requires.txt
brigade.egg-info/top_level.txt
brigade/core/__init__.py
brigade/core/configuration.py
brigade/core/exceptions.py
brigade/core/inventory.py
brigade/core/task.py
brigade/core/helpers/__init__.py
brigade/core/helpers/jinja_helper.py
brigade/plugins/__init__.py
brigade/plugins/functions/__init__.py
brigade/plugins/functions/text/__init__.py
brigade/plugins/inventory/__init__.py
brigade/plugins/inventory/ansible.py
brigade/plugins/inventory/nsot.py
brigade/plugins/inventory/simple.py
brigade/plugins/tasks/__init__.py
brigade/plugins/tasks/apis/__init__.py
brigade/plugins/tasks/apis/http_method.py
brigade/plugins/tasks/commands/__init__.py
brigade/plugins/tasks/commands/command.py
brigade/plugins/tasks/commands/remote_command.py
brigade/plugins/tasks/connections/__init__.py
brigade/plugins/tasks/connections/napalm_connection.py
brigade/plugins/tasks/connections/netmiko_connection.py
brigade/plugins/tasks/connections/paramiko_connection.py
brigade/plugins/tasks/data/__init__.py
brigade/plugins/tasks/data/load_json.py
brigade/plugins/tasks/data/load_yaml.py
brigade/plugins/tasks/files/__init__.py
brigade/plugins/tasks/files/sftp.py
brigade/plugins/tasks/files/write_file.py
brigade/plugins/tasks/networking/__init__.py
brigade/plugins/tasks/networking/napalm_cli.py
brigade/plugins/tasks/networking/napalm_configure.py
brigade/plugins/tasks/networking/napalm_get.py
brigade/plugins/tasks/networking/napalm_validate.py
brigade/plugins/tasks/networking/netmiko_file_transfer.py
brigade/plugins/tasks/networking/netmiko_send_command.py
brigade/plugins/tasks/networking/netmiko_send_config.py
brigade/plugins/tasks/networking/tcp_ping.py
brigade/plugins/tasks/text/__init__.py
brigade/plugins/tasks/text/template_file.py
brigade/plugins/tasks/text/template_string.py