Metadata-Version: 1.1
Name: brigade
Version: 0.0.7
Summary: Fighting fire with fire
Home-page: https://github.com/brigade-automation/brigade
Author: dbarrosop@dravetech.com
Author-email: UNKNOWN
License: Apache License, version 2
Platform: any
Classifier: Development Status :: 4 - Beta
Classifier: Programming Language :: Python :: 2.7
Classifier: Programming Language :: Python :: 3
Classifier: Programming Language :: Python :: 3.4
Classifier: Programming Language :: Python :: 3.5
Classifier: Programming Language :: Python :: 3.6
